aoc_tools/__init__.py
aoc_tools/_advent_timer.py
aoc_tools_dannyboywoop-1.2.0.dist-info/LICENSE
aoc_tools_dannyboywoop-1.2.0.dist-info/METADATA
aoc_tools_dannyboywoop-1.2.0.dist-info/WHEEL
aoc_tools_dannyboywoop-1.2.0.dist-info/top_level.txt
aoc_tools_dannyboywoop-1.2.0.dist-info/RECORD
