Metadata-Version: 2.1
Name: aoc-tools-dannyboywoop
Version: 1.2.0
Summary: AdventOfCode tools.
Home-page: https://github.com/dannyboywoop/AOC_Tools
Author: Daniel Holmes
Author-email: DanielJHolmes@hotmail.co.uk
License: UNKNOWN
Platform: UNKNOWN
Classifier: Programming Language :: Python :: 3
Classifier: License :: OSI Approved :: MIT License
Classifier: Operating System :: OS Independent
Requires-Python: >=3.6
